test/__init__.py
test/test_beacon_api.py
test/test_beacon_concept.py
test/test_beacon_concept_category.py
test/test_beacon_concept_detail.py
test/test_beacon_concept_with_details.py
test/test_beacon_knowledge_map_object.py
test/test_beacon_knowledge_map_predicate.py
test/test_beacon_knowledge_map_statement.py
test/test_beacon_knowledge_map_subject.py
test/test_beacon_predicate.py
test/test_beacon_statement.py
test/test_beacon_statement_annotation.py
test/test_beacon_statement_citation.py
test/test_beacon_statement_object.py
test/test_beacon_statement_predicate.py
test/test_beacon_statement_subject.py
test/test_beacon_statement_with_details.py
test/test_exact_match_response.py
tkbeacon/__init__.py
tkbeacon/api_client.py
tkbeacon/configuration.py
tkbeacon/rest.py
tkbeacon/utils.py
tkbeacon/api/__init__.py
tkbeacon/api/beacon_api.py
tkbeacon/models/__init__.py
tkbeacon/models/beacon_concept.py
tkbeacon/models/beacon_concept_category.py
tkbeacon/models/beacon_concept_detail.py
tkbeacon/models/beacon_concept_with_details.py
tkbeacon/models/beacon_knowledge_map_object.py
tkbeacon/models/beacon_knowledge_map_predicate.py
tkbeacon/models/beacon_knowledge_map_statement.py
tkbeacon/models/beacon_knowledge_map_subject.py
tkbeacon/models/beacon_predicate.py
tkbeacon/models/beacon_statement.py
tkbeacon/models/beacon_statement_annotation.py
tkbeacon/models/beacon_statement_citation.py
tkbeacon/models/beacon_statement_object.py
tkbeacon/models/beacon_statement_predicate.py
tkbeacon/models/beacon_statement_subject.py
tkbeacon/models/beacon_statement_with_details.py
tkbeacon/models/exact_match_response.py
tkbeacon-1.3.0.post2.dist-info/LICENSE
tkbeacon-1.3.0.post2.dist-info/METADATA
tkbeacon-1.3.0.post2.dist-info/WHEEL
tkbeacon-1.3.0.post2.dist-info/top_level.txt
tkbeacon-1.3.0.post2.dist-info/RECORD
